README.md
setup.cfg
setup.py
list_tools/__init__.py
list_tools.egg-info/PKG-INFO
list_tools.egg-info/SOURCES.txt
list_tools.egg-info/dependency_links.txt
list_tools.egg-info/top_level.txt