Metadata-Version: 2.1
Name: list-tools
Version: 0.0.1
Summary: various list helpers. only chunking, atm
Home-page: https://github.com/kosovojs/list_tools
Author: Edgars Košovojs
Author-email: kosovojs@gmail.com
License: MIT
Keywords: lists,split,chunk,helpers
Platform: UNKNOWN
Classifier: Development Status :: 3 - Alpha
Classifier: Intended Audience :: Developers
Classifier: License :: OSI Approved :: MIT License
Classifier: Programming Language :: Python :: 3
